{
  "sections": {
    "fa7c9790-f222-4e39-81ff-1b1f25ad72cf": {
      "type": "full-width-banner",
      "settings": {
        "enable_background": false,
        "background_color": "",
        "content_position_vertical": "items-center",
        "content_position_horizontal": "justify-center",
        "title": "",
        "subtitle": "",
        "cta_text": "",
        "cta_link": "",
        "cta_text_second": "",
        "cta_link_second": "",
        "image_mobile": "shopify:\/\/shop_images\/Starlight-Hero-Banner-Mobile_c9eedc09-1d46-4ec9-b230-3f0a2252c01b.png",
        "image": "shopify:\/\/shop_images\/Starlight-Hero-Banner-Desktop_d9113bb4-4cf9-4035-871c-b208425f0e3c.png"
      }
    },
    "b6d7c71a-367b-4752-8cbb-b83dcb4b3c3e": {
      "type": "two-up-reverse-cms",
      "disabled": true,
      "settings": {
        "image": "shopify:\/\/shop_images\/AboutUs_Starlight_02.jpg",
        "title": "Platinum Health Supply Group & Starlight Children's Foundation Partnership",
        "description": "<p>Platinum Health’s aim is to help the Starlight foundation through its customers. Join us in brightening the lives of seriously ill-children and their families.<\/p>",
        "cta_link": ""
      }
    },
    "5bea124a-61f3-4a5b-b65a-d0eaa521b7b8": {
      "type": "two-up",
      "settings": {
        "image": "shopify:\/\/shop_images\/Starlight-Image-02_0f7f9455-14ad-47da-9174-435149db8e33.png",
        "is_reversed": false,
        "background_color": "#ffffff",
        "title": "Starlight's vision is that everyone experiences a happy childhood, because happiness matters.",
        "description": "Serious childhood illness doesn’t just impact a child’s health. It can turn their whole life upside down, causing them to miss out on spending time with their family, building friendships, going to school and just living their life. Australia has one of the best healthcare systems in the world. But sick children and young people need more than the exceptional care that our clinicians can offer. They need the social and emotional support that lets them be a child.\n\nFor over 30 years, the Starlight Foundation have used play, social connection and creativity to support children and young people in some of their toughest times and to positively change their healthcare experience.",
        "cta_as_button": false,
        "cta_text": "",
        "cta_url": "",
        "margin_top": 0,
        "margin_bottom": 0,
        "margin_top_mobile": 24,
        "margin_bottom_mobile": 24
      }
    },
    "38c02ab2-44ae-423b-819d-0a363f45e108": {
      "type": "two-up",
      "settings": {
        "image": "shopify:\/\/shop_images\/Starlight-Image-03.png",
        "is_reversed": true,
        "background_color": "#ffffff",
        "title": "Platinum Health is committed to supporting the Starlight Children's Foundation through our customer base.",
        "description": "Our partnership with Starlight is an exciting opportunity for us to make a significant impact on the lives of children and their families who are facing serious illnesses. We believe that by working together, we can provide not just essential supplies, but also hope and happiness to those who are going through difficult times. Our shared goal is to help children and their families experience the joy and wonder of childhood, even during difficult circumstances. We are proud to join forces with Starlight and become one of their trusted partners.\n\nTogether, we can deliver not just critical supplies, but something even more special – HOPE.",
        "cta_as_button": false,
        "cta_text": "",
        "cta_url": "",
        "margin_top": 0,
        "margin_bottom": 0,
        "margin_top_mobile": 24,
        "margin_bottom_mobile": 24
      }
    },
    "842695e3-79b6-4511-b930-ee07b3cd6a3e": {
      "type": "icon-with-text",
      "blocks": {
        "template--21585692033344__842695e3-79b6-4511-b930-ee07b3cd6a3e-item-1": {
          "type": "item",
          "settings": {
            "image": "shopify:\/\/shop_images\/image_5.svg",
            "title": "",
            "description": "<p><strong>Over $50,000 Contributed to Starlight Children's Foundation.<\/strong><\/p>",
            "content_position_vertical": "items-center",
            "icon_position": "flex-row"
          }
        },
        "template--21585692033344__842695e3-79b6-4511-b930-ee07b3cd6a3e-item-2": {
          "type": "item",
          "settings": {
            "image": "shopify:\/\/shop_images\/image_5_1.svg",
            "title": "",
            "description": "<p><strong>Starlight Children's Silver Partner Since 2020<\/strong><\/p>",
            "content_position_vertical": "items-center",
            "icon_position": "flex-row"
          }
        },
        "template--21585692033344__842695e3-79b6-4511-b930-ee07b3cd6a3e-item-3": {
          "type": "item",
          "settings": {
            "image": "shopify:\/\/shop_images\/image_5_2.svg",
            "title": "",
            "description": "<p><strong>Ongoing Support For Starlight Children's Foundation<\/strong><\/p>",
            "content_position_vertical": "items-center",
            "icon_position": "flex-row"
          }
        },
        "b08bd01e-a579-45da-b162-7290d4a243d2": {
          "type": "item",
          "settings": {
            "image": "shopify:\/\/shop_images\/image_5_3.svg",
            "title": "",
            "description": "<p><strong>Licensed Starlight Brand Merchandise Partner<\/strong><\/p>",
            "content_position_vertical": "items-center",
            "icon_position": "flex-row"
          }
        }
      },
      "block_order": [
        "template--21585692033344__842695e3-79b6-4511-b930-ee07b3cd6a3e-item-1",
        "template--21585692033344__842695e3-79b6-4511-b930-ee07b3cd6a3e-item-2",
        "template--21585692033344__842695e3-79b6-4511-b930-ee07b3cd6a3e-item-3",
        "b08bd01e-a579-45da-b162-7290d4a243d2"
      ],
      "settings": {
        "title": ""
      }
    },
    "053fc7a0-0b04-43fc-923b-d5c05b3993d4": {
      "type": "column-banner",
      "disabled": true,
      "settings": {
        "class_modify": "column-banner-cms",
        "bg_color": "#ffffff",
        "image_mobile": "shopify:\/\/shop_images\/Image_2_d9613f63-fc53-4f97-85dd-40dd17e2bf05.svg",
        "image": "shopify:\/\/shop_images\/Image_2e8f7e95-02c7-48b0-9426-5eec1f9fce39.svg",
        "url": "#"
      }
    },
    "6a091df4-adcf-4b05-96db-820f4c81fffc": {
      "type": "video-cms",
      "settings": {
        "video_type": "mp4",
        "video_url": "https:\/\/cdn.shopify.com\/videos\/c\/o\/v\/67d488389c67445cb5a555e001ac7825.mp4",
        "video_type_mobile": "mp4",
        "video_url_mobile": "https:\/\/cdn.shopify.com\/videos\/c\/o\/v\/67d488389c67445cb5a555e001ac7825.mp4"
      }
    },
    "27635293-34fa-49a6-b1ae-de84d03305ed": {
      "type": "product-donate",
      "settings": {
        "text_color": "#2d2e31",
        "heading": "Every partner product bought will be donated to the foundation",
        "product": "safeguard-medical-children-mask-blue-starlight-childrens-foundation-mask-australian-made"
      }
    },
    "d8897e15-7c83-42f0-8b75-59c910b31d03": {
      "type": "three-up-column",
      "blocks": {
        "3a0b59a7-6dec-4039-9cfc-479cbc01a413": {
          "type": "card",
          "settings": {
            "image": "shopify:\/\/shop_images\/image_4.svg",
            "title": "Donate to sick kids",
            "description": "Your incredible gift will create laughter during the toughest of times. Bring happiness to a seriously ill child by making a donation today\u2028",
            "cta_text": "Donate",
            "url": "https:\/\/www.starlight.org.au\/support-us\/donate-to-starlight\/donate-to-bring-happiness-to-sick-kids"
          }
        },
        "6634d708-bdbb-49b5-8bbe-0d0ee045fd15": {
          "type": "card",
          "settings": {
            "image": "shopify:\/\/shop_images\/image_4_1.svg",
            "title": "Donate goods and services",
            "description": "We accept goods and services that will contribute to the success of our Starlight Express Rooms, Livewire and Wish granting programs",
            "cta_text": "Donate",
            "url": "https:\/\/www.starlight.org.au\/support-us\/donate-to-starlight\/donate-goods-and-services"
          }
        },
        "a7bee651-c1f7-48d5-ac6c-ada9d4812bb9": {
          "type": "card",
          "settings": {
            "image": "shopify:\/\/shop_images\/image_4_2.svg",
            "title": "Shop our partners",
            "description": "Help sick kids while you shop! You could be making a difference simply by shopping with our partners who champion our cause.\u2028",
            "cta_text": "Buy now",
            "url": "shopify:\/\/products\/safeguard-medical-children-mask-blue-starlight-childrens-foundation-mask-australian-made"
          }
        }
      },
      "block_order": [
        "3a0b59a7-6dec-4039-9cfc-479cbc01a413",
        "6634d708-bdbb-49b5-8bbe-0d0ee045fd15",
        "a7bee651-c1f7-48d5-ac6c-ada9d4812bb9"
      ],
      "custom_css": [

      ],
      "settings": {
        "bg_color": "#52288e",
        "heading": "Support Starlight"
      }
    },
    "8ab3e314-1324-4430-8f95-7648451150f0": {
      "type": "contact-module",
      "settings": {
        "text_color": "#2d2e31",
        "heading": "Be part of our social mission",
        "description": "<p>Fill out the form below and let us know if you are interested in an opportunity with Platinum, we will then be in contact with you.<\/p>",
        "form_script": "<script src=\"\/\/customercare.platinumhealthsupply.com.au\/resources\/sharing\/embed.js?sharing=lp-embed&domain=customercare.platinumhealthsupply.com.au&id=7L45-A2R%2F%22\"><\/script>"
      }
    }
  },
  "order": [
    "fa7c9790-f222-4e39-81ff-1b1f25ad72cf",
    "b6d7c71a-367b-4752-8cbb-b83dcb4b3c3e",
    "5bea124a-61f3-4a5b-b65a-d0eaa521b7b8",
    "38c02ab2-44ae-423b-819d-0a363f45e108",
    "842695e3-79b6-4511-b930-ee07b3cd6a3e",
    "053fc7a0-0b04-43fc-923b-d5c05b3993d4",
    "6a091df4-adcf-4b05-96db-820f4c81fffc",
    "27635293-34fa-49a6-b1ae-de84d03305ed",
    "d8897e15-7c83-42f0-8b75-59c910b31d03",
    "8ab3e314-1324-4430-8f95-7648451150f0"
  ]
}